{"id":"costumes/circuit.json","name":"Circuit Costume","thumbnail":"https://mcstore.io/image/xforgeassets002.xboxlive.com/pf-title-b63a0803d3653643-20ca2/27d6d4c4-661a-4aed-94a2-fd4bc6ca45dc/circuit_Thumbnail_0.jpg","price":{"type":"Minecoins","amount":"310"},"description":"You've heard of a gaming computer, but have you heard of a computer gaming?","source":"Store","type":"Costume","obtainable":true,"date":"N/A","keywords":"Costume, Store, Obtainable, Circuit, Screen, Hoodie, Robot","similar":["avatars/circuit.json","titles/circuit.json"]}